License.md
MANIFEST.in
Readme.md
Readme_rst.rst
require.txt
setup.py
usage.txt
Push_To_Wordpress.egg-info/PKG-INFO
Push_To_Wordpress.egg-info/SOURCES.txt
Push_To_Wordpress.egg-info/dependency_links.txt
Push_To_Wordpress.egg-info/entry_points.txt
Push_To_Wordpress.egg-info/requires.txt
Push_To_Wordpress.egg-info/top_level.txt
push_to_wordpress/__init__.py
push_to_wordpress/configdemo.ini
push_to_wordpress/presser.py