Metadata-Version: 1.0
Name: Push-To-Wordpress
Version: 0.15
Summary: a commandline tool to post to Markdown files to wordpress posts (based on wordpress XML-RPC)
Home-page: https://github.com/alonisser/PushToWordpress
Author: Alonisser
Author-email: alonisser@gmail.com
License: OSI Approved :: MIT License
Keywords: blogging wordpress commandline
Platform: UNKNOWN
Classifier: Development Status :: 3 - Alpha
Classifier: Environment :: Console
Classifier: Intended Audience :: Other Audience
Classifier: Intended Audience :: Developers
Classifier: Natural Language :: English
Classifier: License :: OSI Approved :: MIT License
Classifier: Programming Language :: Python
Classifier: Programming Language :: Python :: 2.7
Classifier: Topic :: Internet :: WWW/HTTP :: Site Management
